{
    "PageTitle": "ocsp nonce enable",
    "FuncDef": "The ocsp nonce enable command adds a nonce extension to the OCSP request sent by a PKI entity.\nThe undo ocsp nonce enable command cancels the configuration. The ocsp nonce enable command adds a nonce extension to the OCSP request sent by a PKI entity. The undo ocsp nonce enable command cancels the configuration. By default, the OCSP request sent by a PKI entity contains a nonce extension.",
    "CLIs": [
        "ocsp nonce enable",
        "undo ocsp nonce enable"
    ],
    "ParentView": [
        "PKI domain view"
    ],
    "ParaDef": [],
    "Examples": [
        [
            "<HUAWEI> system-view",
            "[~HUAWEI] pki realm test",
            "[*HUAWEI-pki-realm-test] ocsp nonce enable"
        ]
    ],
    "ExtraInfo": ""
}