{
    "PageTitle": "pki certificate access-control-policy name",
    "FuncDef": "The pki certificate access-control-policy name command creates a certificate access policy and enters the certificate access policy view, or displays the view of an existing certificate access policy.\nThe undo pki certificate access-control-policy name command deletes a certificate access policy. The pki certificate access-control-policy name command creates a certificate access policy and enters the certificate access policy view, or displays the view of an existing certificate access policy. The undo pki certificate access-control-policy name command deletes a certificate access policy. By default, no certificate access policy is created.",
    "CLIs": [
        "pki certificate access-control-policy name <policy-name>",
        "undo pki certificate access-control-policy name <policy-name>"
    ],
    "ParentView": [
        "System view"
    ],
    "ParaDef": [
        {
            "Parameters": "name <policy-name>",
            "Info": "Specifies the name of a certificate access policy.\nThe value is a string of 1 to 32 case-insensitive characters, spaces and question marks (?) not supported. The character string can contain spaces if it is enclosed with double quotation marks (\"\")."
        }
    ],
    "Examples": [
        [
            "<HUAWEI> system-view",
            "[~HUAWEI] pki certificate access-control-policy name policy1"
        ]
    ],
    "ExtraInfo": ""
}