{
    "PageTitle": "option121",
    "FuncDef": "The option121 command configures the classless static route for the DHCP client. The undo option121 command deletes a configured classless static route. By default, no classless static route is configured.",
    "CLIs": [
        "option121 ip-address { <ip-address> <mask-length> <gateway-address> } &<1-8>",
        "undo option121 [ ip-address <ip-address> <mask-length> <gateway-address> ]"
    ],
    "ParentView": [
        "IP address pool view"
    ],
    "ParaDef": [
        {
            "Parameters": "ip-address <ip-address>",
            "Info": "Specifies a destination IP address.\nThe value is in dotted decimal notation."
        },
        {
            "Parameters": "<mask-length>",
            "Info": "Specifies a mask length.\nThe value is an integer ranging from 0 to 32."
        },
        {
            "Parameters": "<gateway-address>",
            "Info": "Specifies a gateway address.\nThe value is in dotted decimal notation."
        }
    ],
    "Examples": [
        [
            "<HUAWEI> system-view",
            "[~HUAWEI] ip pool global1",
            "[*HUAWEI-ip-pool-global1] option121 ip-address 10.10.10.10 24 10.11.11.11"
        ]
    ],
    "ExtraInfo": "The option121 command applies to only the DHCP server. The option121 command configures Option 121 that defines a classless static route allocated to a client."
}