{
    "PageTitle": "nqa jitter tag-version",
    "FuncDef": "The nqa jitter tag-version command sets the packet version for a jitter test instance.\nThe undo nqa jitter tag-version command restores the default configuration. The nqa jitter tag-version command sets the packet version for a jitter test instance. The undo nqa jitter tag-version command restores the default configuration. By default, the packet version in a jitter test instance is 1.",
    "CLIs": [
        "nqa jitter tag-version <version-number>",
        "undo nqa jitter tag-version"
    ],
    "ParentView": [
        "System view"
    ],
    "ParaDef": [
        {
            "Parameters": "<version-number>",
            "Info": "Specifies the version of packets.\nThe value can be 1 or 2."
        }
    ],
    "Examples": [
        [
            "<HUAWEI> system-view",
            "[~HUAWEI] nqa jitter tag-version 2"
        ]
    ],
    "ExtraInfo": "Packet statistics in version 2 is more accurate than those in version 1. Version 2 is recommended."
}