{
    "PageTitle": "timer query",
    "FuncDef": "The timer query command sets a global interval for sending IGMP general query messages.\nThe undo timer query command restores the default value. The timer query command sets a global interval for sending IGMP general query messages. The undo timer query command restores the default value. By default, the interval for sending IGMP general query messages is 60 seconds.",
    "CLIs": [
        "timer query <interval>",
        "undo timer query"
    ],
    "ParentView": [
        "IGMP view,VPN instance IGMP view"
    ],
    "ParaDef": [
        {
            "Parameters": "<interval>",
            "Info": "Specifies an interval for sending IGMP general query messages.\nThe value is an integer ranging from 1 to 18000, in seconds."
        }
    ],
    "Examples": [
        [
            "<HUAWEI> system-view",
            "[~HUAWEI] multicast routing-enable",
            "[*HUAWEI] igmp",
            "[*HUAWEI-igmp] timer query 125"
        ]
    ],
    "ExtraInfo": ""
}