{
    "PageTitle": "lock (user view)",
    "FuncDef": "The lock command locks the current user interface to prevent unauthorized access to the device. The lock command locks the current user interface to prevent unauthorized access to the device.",
    "CLIs": [
        "lock"
    ],
    "ParentView": [
        "User view"
    ],
    "ParaDef": [],
    "Examples": [
        [
            "<HUAWEI> lock"
        ]
    ],
    "ExtraInfo": "To prevent other users from accessing the device, you can run the lock command to lock the user interface. The user interface can be the console interface and VTY interface."
}