{
    "PageTitle": "display ifit flow-cache",
    "FuncDef": "The display ifit flow-cache command displays IFIT flow table information. The display ifit flow-cache command displays IFIT flow table information. This command is supported only on the CE6855-48XS8CQ, CE6885-SAN, CE8855, CE8851-32CQ4BQ, CE6885, CE6885-T, CE6885-LL (standard forwarding mode) and CE6863E-48S8CQ.",
    "CLIs": [
        "display ifit flow-cache [ { tcp | udp } | sip <ipv4-sip-address> | dip <ipv4-dip-address> | srcport <srcport-number> | dstport <dstport-number> | status { active | aged } | flow-id <flow-id-number> ] slot <slot-id>",
        "display ifit flow-cache [ { tcp | udp } | sip <ipv6-sip-address> | dip <ipv6-dip-address> | srcport <srcport-number> | dstport <dstport-number> | status { active | aged } | flow-id <flow-id-number> ] slot <slot-id>"
    ],
    "ParentView": [
        "All views"
    ],
    "ParaDef": [
        {
            "Parameters": "tcp",
            "Info": "Indicates TCP packets.\n-"
        },
        {
            "Parameters": "udp",
            "Info": "Indicates UDP packets.\n-"
        },
        {
            "Parameters": "sip <ipv4-sip-address>",
            "Info": "Indicates source IPv4 address.\nThe value is in dotted decimal notation."
        },
        {
            "Parameters": "sip <ipv6-sip-address>",
            "Info": "Indicates source IPv6 address.\nThe value is a 32-digit hexadecimal number in the format X:X:X:X:X:X:X:X."
        },
        {
            "Parameters": "dip <ipv4-dip-address>",
            "Info": "Indicates destination IPv4 address.\nThe value is in dotted decimal notation."
        },
        {
            "Parameters": "dip <ipv6-dip-address>",
            "Info": "Indicates destination IPv6 address.\nThe value is a 32-digit hexadecimal number in the format X:X:X:X:X:X:X:X."
        },
        {
            "Parameters": "srcport <srcport-number>",
            "Info": "Specifies the source port.\nThe value is an integer in the range of 0 to 65535."
        },
        {
            "Parameters": "dstport <dstport-number>",
            "Info": "Specifies the destination port number.\nThe value is an integer in the range of 0 to 65535."
        },
        {
            "Parameters": "status",
            "Info": "Specifies the flow table status.\n-"
        },
        {
            "Parameters": "active",
            "Info": "Sets the flow table status to active.\n-"
        },
        {
            "Parameters": "aged",
            "Info": "Indicates that the flow table is aged.\n-"
        },
        {
            "Parameters": "flow-id <flow-id-number>",
            "Info": "Specifies a flow ID.\nThe value is an integer that ranges from 0 to 1099511627775."
        },
        {
            "Parameters": "slot <slot-id>",
            "Info": "Specifies the slot ID.\nThe value is a string of 1 to 31 case-sensitive characters, spaces not supported."
        }
    ],
    "Examples": [
        [
            "<HUAWEI> display ifit flow-cache slot 1"
        ]
    ],
    "ExtraInfo": ""
}