{
    "From": " Cisco IOS Configuration Fundamentals Command Reference",
    "PageTitle": "show subsys",
    "FuncDef": [
        "To display the subsystem information, use the **show subsys** command in privileged EXEC mode. "
    ],
    "CLIs": [
        "show subsys [ class<class> | name <name> ]"
    ],
    "ParentView": [
        null
    ],
    "ParaDef": [
        {
            "Parameters": " **class***class* ",
            "Info": " (Optional) Displays the subsystems of the specified class. Valid classes are **driver**, **ehsa**,**ifs**, **kernel**, **library**, **license**, **management**, **microcode**, **pre-ehsa**, **predriver**, **protocol**, **registry**,and **sysinit**. "
        },
        {
            "Parameters": " **name** *name* ",
            "Info": " (Optional) Displays the specified subsystem. Use the asterisk character (*) as a wildcard at the end of the name to list all subsystems, starting with the specified characters. "
        }
    ],
    "Examples": [
        [
            "The following is sample output from the show subsys command:",
            "```",
            "Router# show subsys",
            "```",
            "```",
            "```",
            "```",
            "Name Class Version",
            "```",
            "```",
            "static_map Kernel 1.000.001",
            "```",
            "```",
            "arp Kernel 1.000.001",
            "```",
            "```",
            "ether Kernel 1.000.001",
            "```",
            "```",
            "compress Kernel 1.000.001",
            "```",
            "```",
            "alignment Kernel 1.000.002",
            "```",
            "```",
            "monvar Kernel 1.000.001",
            "```",
            "```",
            "slot Kernel 1.000.001",
            "```",
            "```",
            "oir Kernel 1.000.001",
            "```",
            "```",
            "atm Kernel 1.000.001",
            "```",
            "```",
            "ip_addrpool_sys Library 1.000.001",
            "```",
            "```",
            "chat Library 1.000.001",
            "```",
            "```",
            "dialer Library 1.000.001",
            "```",
            "```",
            "flash_services Library 1.000.001",
            "```",
            "```",
            "ip_localpool_sys Library 1.000.001",
            "```",
            "```",
            "nvram_common Driver 1.000.001",
            "```",
            "```",
            "ASP Driver 1.000.001",
            "```",
            "```",
            "sonict Driver 1.000.001",
            "```",
            "```",
            "oc3suni Driver 1.000.001",
            "```",
            "```",
            "oc12suni Driver 1.000.001",
            "```",
            "```",
            "ds3suni Driver 1.000.001",
            "```",
            "The following is sample output from the show subsys command that includes the license class:",
            "```",
            "Router# show subsys name license",
            "```",
            "```",
            "```",
            "```",
            "Name Class Version",
            "```",
            "```",
            "license_mgmt_local Management 1.000.001",
            "```",
            "```",
            "license_admin_local Management 1.000.001",
            "```",
            "```",
            "license_debug_core Management 1.000.001",
            "```",
            "```",
            "license_test_ui Management 1.000.001",
            "```",
            "```",
            "test_license_parser Management 1.000.001",
            "```",
            "```",
            "license_ui Management 1.000.001",
            "```",
            "```",
            "license_parser Management 1.000.001",
            "```",
            "```",
            "license_registry Registry 1.000.001",
            "```",
            "```",
            "license_client License 1.000.001",
            "```",
            "```",
            "```",
            "[ Table 158 ] (#wp1477710) describes the fields shown in the display.",
            "Table 158 show subsys Field Descriptions",
            "| Field | Description |",
            "| --- | --- |",
            "| Name | Name of the subsystem. |",
            "| Class | Class of the subsystem. Possible classes include Driver, Ehsa, Ifs, Kernel, Library, License, Management, Microcode, Pre-Ehsa, Pre-driver, Protocol, Registry, and Sysinit. |",
            "| Version | Version of the subsystem. |"
        ]
    ],
    "ExtraInfo": "Use the **show subsys** command to confirm that all required features are in the running image.",
    "RelatedCmds": []
}