{
    "PageTitle": "igmp snooping querier enable (Bridge domain view)",
    "FuncDef": "The igmp snooping querier enable command enables a querier in a BD.\nThe undo igmp snooping querier enable command disables a querier in a BD. The igmp snooping querier enable command enables a querier in a BD. The undo igmp snooping querier enable command disables a querier in a BD. By default, queriers are disabled in all BDs. This command is supported only on the CE6863H, CE6863H-K, CE6860-SAN, CE6866K, CE6866, CE6860-HAM, CE6855-48XS8CQ, CE6885-SAN, CE8850-SAN, CE8855, CE8851-32CQ4BQ, CE8851K, CE8851-32CQ8DQ-P, CE8850-HAM, CE6881H, CE6881H-K, CE6885, CE6885-T, CE6885-LL (standard forwarding mode) and CE6863E-48S8CQ.",
    "CLIs": [
        "igmp snooping querier enable",
        "undo igmp snooping querier enable"
    ],
    "ParentView": [
        "Bridge domain view"
    ],
    "ParaDef": [],
    "Examples": [
        [
            "<HUAWEI> system-view",
            "[~HUAWEI] igmp snooping enable",
            "[*HUAWEI] bridge-domain 10",
            "[*HUAWEI-bd10] igmp snooping querier enable"
        ]
    ],
    "ExtraInfo": "After the querier function is enabled on a Layer 2 device, this device will replace its upstream device to send IGMP Query messages, and will be able to create and maintain multicast forwarding entries at the data link layer, implementing multicast data forwarding.\nThe following conditions must be met before the igmp snooping querier enable command is run:"
}