{
    "PageTitle": "multicast layer-2 invalid-packet igmp snooping",
    "FuncDef": "The multicast layer-2 invalid-packet igmp snooping command sets the maximum number of invalid Layer 2 multicast protocol packets allowed on a device.\nThe undo multicast layer-2 invalid-packet igmp snooping command deletes the set maximum number of invalid Layer 2 multicast protocol packets allowed on a device. The multicast layer-2 invalid-packet igmp snooping command sets the maximum number of invalid Layer 2 multicast protocol packets allowed on a device. The undo multicast layer-2 invalid-packet igmp snooping command deletes the set maximum number of invalid Layer 2 multicast protocol packets allowed on a device. By default, a multicast device can store a maximum of 10 invalid Layer 2 multicast protocol packets.",
    "CLIs": [
        "multicast layer-2 invalid-packet igmp snooping max-count <max-Num>",
        "undo multicast layer-2 invalid-packet igmp snooping"
    ],
    "ParentView": [
        "System view"
    ],
    "ParaDef": [
        {
            "Parameters": "max-count <max-Num>",
            "Info": "Specifies the maximum number of invalid packets allowed on a device.\nThe value is an integer ranging from 1 to 100."
        }
    ],
    "Examples": [
        [
            "<HUAWEI> system-view",
            "[~HUAWEI] multicast layer-2 invalid-packet igmp snooping max-count 20"
        ]
    ],
    "ExtraInfo": ""
}