{
    "From": " Cisco IOS Configuration Fundamentals Command Reference",
    "PageTitle": "clear vlan counters",
    "FuncDef": [
        "To clear the software-cached counter values to start from zero again for a specified VLAN or all existing VLANs, use the **clear vlan counters** command in privileged EXEC mode. "
    ],
    "CLIs": [
        "clear vlan [ <vlan-id> ] counters"
    ],
    "ParentView": [
        null
    ],
    "ParaDef": [
        {
            "Parameters": " *vlan-id* ",
            "Info": " (Optional) The ID of a specific VLAN. Range: 1 to 4094. "
        }
    ],
    "Examples": [
        [
            "```",
            "Router# clear vlan 10 counters",
            "```",
            "```",
            "Clear \"show vlan\" counters on this vlan [ confirm ] y",
            "```",
            "```",
            "Router#",
            "```"
        ]
    ],
    "ExtraInfo": "If you do not specify a *vlan-id*; the software-cached counter values for all existing VLANs are cleared.",
    "RelatedCmds": [
        {
            "cmd": " **show vlan counters** ",
            "description": " Displays the software-cached counter values. "
        }
    ]
}