{
    "From": " Cisco IOS Configuration Fundamentals Command Reference",
    "PageTitle": "parser command serializer",
    "FuncDef": [
        "To enable configuration access only to the users holding a configuration lock and to prevent other clients from accessing the running configuration, use the **parser command serializer** command in global configuration mode. To disable this configuration, use the **no** form of this command. "
    ],
    "CLIs": [
        "parser command serializer",
        "no parser command serializer"
    ],
    "ParentView": [
        null
    ],
    "ParaDef": [
        {
            "Parameters": "No parameters.",
            "Info": "This commmand has no arguments or keywords."
        }
    ],
    "Examples": [
        [
            "The following example shows how to configure the Parser Concurrency and Locking Improvements feature:",
            "```",
            "Router# configure terminal",
            "```",
            "```",
            "Router(config)# parser command serializer",
            "```"
        ]
    ],
    "ExtraInfo": "The Parser Concurrency and Locking Improvements feature ensures that exclusive access is granted only to a requested process and prevents other users from concurrently accessing the Cisco IOS configuration. That is, it prevents simultaneous execution of two or more commands. Use the **parser command serializer** command to configure the Parser Concurrency and Locking Improvements feature.",
    "RelatedCmds": [
        {
            "cmd": " **configuration mode exclusive** ",
            "description": " Enables single-user (exclusive) access functionality for the Cisco IOS CLI. "
        },
        {
            "cmd": " **configure terminal lock** ",
            "description": " Locks the running configuration into exclusive configuration mode for the duration of your configuration session. "
        },
        {
            "cmd": " **test parser session-lock** ",
            "description": " Tests the behavior of the Parser Concurrency and Locking Improvements feature. "
        }
    ]
}