{
    "PageTitle": "ntp authentication enable",
    "FuncDef": "The ntp authentication enable command enables identity authentication for NTP.\nThe undo ntp authentication enable command disables identity authentication. The ntp authentication enable command enables identity authentication for NTP. The undo ntp authentication enable command disables identity authentication. By default, identity authentication is disabled.",
    "CLIs": [
        "ntp authentication enable",
        "undo ntp authentication enable"
    ],
    "ParentView": [
        "System view"
    ],
    "ParaDef": [],
    "Examples": [
        [
            "<HUAWEI> system-view",
            "[~HUAWEI] ntp authentication enable"
        ]
    ],
    "ExtraInfo": "NTP authentication can be used on networks that require high security."
}