{
    "From": " Cisco IOS Configuration Fundamentals Command Reference",
    "PageTitle": "terminal parity",
    "FuncDef": [
        "To define the generation of the parity bit for the current terminal line and session, use the **terminal parity** command in EXEC mode. "
    ],
    "CLIs": [
        "terminal parity { none | even | odd | space | mark }"
    ],
    "ParentView": [
        null
    ],
    "ParaDef": [
        {
            "Parameters": " **none** ",
            "Info": " No parity. This is the default. "
        },
        {
            "Parameters": " **even** ",
            "Info": " Even parity. "
        },
        {
            "Parameters": " **odd** ",
            "Info": " Odd parity. "
        },
        {
            "Parameters": " **space** ",
            "Info": " Space parity. "
        },
        {
            "Parameters": " **mark** ",
            "Info": " Mark parity. "
        }
    ],
    "Examples": [
        [
            "In the following example, odd parity checking is enabled for the current session:",
            "```",
            "Router# terminal parity odd",
            "```"
        ]
    ],
    "ExtraInfo": "Communication protocols provided by devices such as terminals and modems will sometimes require a specific parity bit setting. Refer to the documentation for your device to determine required parity settings.",
    "RelatedCmds": [
        {
            "cmd": " **parity** ",
            "description": " Defines generation of a parity bit for connections on a specified line or lines. "
        }
    ]
}